pyrinox/__init__.py
pyrinox/pyrino.py
pyrinox-1.0.1.dist-info/METADATA
pyrinox-1.0.1.dist-info/WHEEL
pyrinox-1.0.1.dist-info/top_level.txt
pyrinox-1.0.1.dist-info/RECORD
