Metadata-Version: 2.4
Name: pyrinox
Version: 1.0.1
Summary: A Python library
Home-page: https://t.me/MeAminCoder/3
Author: Amin
Author-email: sinyoramin@gmail.com
Keywords: rubika,api,bot,social-network
Classifier: Development Status :: 4 - Beta
Classifier: Intended Audience :: Developers
Classifier: License :: OSI Approved :: MIT License
Classifier: Programming Language :: Python :: 3.7
Classifier: Programming Language :: Python :: 3.8
Classifier: Programming Language :: Python :: 3.9
Classifier: Programming Language :: Python :: 3.10
Classifier: Programming Language :: Python :: 3.11
Classifier: Programming Language :: Python :: 3.12
Classifier: Operating System :: OS Independent
Requires-Python: >=3.7
Requires-Dist: aiohttp>=3.11.15
Requires-Dist: aiofiles>=24.1.0
Requires-Dist: tqdm>=4.67.1
Dynamic: author
Dynamic: author-email
Dynamic: classifier
Dynamic: description
Dynamic: description-content-type
Dynamic: home-page
Dynamic: keywords
Dynamic: requires-dist
Dynamic: requires-python
Dynamic: summary
